{
    "uid": "71c3cf0f-a7ad-431c-8b71-23a4ebf00b74",
    "name": "15_CatBoost",
    "preprocessing": [
        {
            "ml_task": "binary_classification",
            "params": {
                "columns_preprocessing": {},
                "target_preprocessing": [
                    "na_exclude"
                ],
                "ml_task": "binary_classification"
            }
        },
        {
            "ml_task": "binary_classification",
            "params": {
                "columns_preprocessing": {},
                "target_preprocessing": [
                    "na_exclude"
                ],
                "ml_task": "binary_classification"
            }
        },
        {
            "ml_task": "binary_classification",
            "params": {
                "columns_preprocessing": {},
                "target_preprocessing": [
                    "na_exclude"
                ],
                "ml_task": "binary_classification"
            }
        },
        {
            "ml_task": "binary_classification",
            "params": {
                "columns_preprocessing": {},
                "target_preprocessing": [
                    "na_exclude"
                ],
                "ml_task": "binary_classification"
            }
        },
        {
            "ml_task": "binary_classification",
            "params": {
                "columns_preprocessing": {},
                "target_preprocessing": [
                    "na_exclude"
                ],
                "ml_task": "binary_classification"
            }
        }
    ],
    "learners": [
        {
            "library_version": "0.26.1",
            "algorithm_name": "CatBoost",
            "algorithm_short_name": "CatBoost",
            "uid": "2ffd4476-f675-4a61-8573-bdc20cb02de4",
            "params": {
                "model_type": "CatBoost",
                "ml_task": "binary_classification",
                "n_jobs": -1,
                "seed": 1237,
                "learning_rate": 0.1,
                "depth": 7,
                "rsm": 1.0,
                "loss_function": "Logloss",
                "eval_metric": "Logloss",
                "explain_level": 2
            },
            "name": "learner_fold_0",
            "best_ntree_limit": 269
        },
        {
            "library_version": "0.26.1",
            "algorithm_name": "CatBoost",
            "algorithm_short_name": "CatBoost",
            "uid": "0364d3b4-8b07-4b93-b0c0-525df827e2ea",
            "params": {
                "model_type": "CatBoost",
                "ml_task": "binary_classification",
                "n_jobs": -1,
                "seed": 1237,
                "learning_rate": 0.1,
                "depth": 7,
                "rsm": 1.0,
                "loss_function": "Logloss",
                "eval_metric": "Logloss",
                "explain_level": 2
            },
            "name": "learner_fold_1",
            "best_ntree_limit": 302
        },
        {
            "library_version": "0.26.1",
            "algorithm_name": "CatBoost",
            "algorithm_short_name": "CatBoost",
            "uid": "35b74019-85c7-4bc4-8cc9-42ff247cec7a",
            "params": {
                "model_type": "CatBoost",
                "ml_task": "binary_classification",
                "n_jobs": -1,
                "seed": 1237,
                "learning_rate": 0.1,
                "depth": 7,
                "rsm": 1.0,
                "loss_function": "Logloss",
                "eval_metric": "Logloss",
                "explain_level": 2
            },
            "name": "learner_fold_2",
            "best_ntree_limit": 458
        },
        {
            "library_version": "0.26.1",
            "algorithm_name": "CatBoost",
            "algorithm_short_name": "CatBoost",
            "uid": "bd8d4f8d-a772-47e7-a1f3-047238aeb6a7",
            "params": {
                "model_type": "CatBoost",
                "ml_task": "binary_classification",
                "n_jobs": -1,
                "seed": 1237,
                "learning_rate": 0.1,
                "depth": 7,
                "rsm": 1.0,
                "loss_function": "Logloss",
                "eval_metric": "Logloss",
                "explain_level": 2
            },
            "name": "learner_fold_3",
            "best_ntree_limit": 294
        },
        {
            "library_version": "0.26.1",
            "algorithm_name": "CatBoost",
            "algorithm_short_name": "CatBoost",
            "uid": "216989b8-fa2c-4e11-9968-efd23e69ec56",
            "params": {
                "model_type": "CatBoost",
                "ml_task": "binary_classification",
                "n_jobs": -1,
                "seed": 1237,
                "learning_rate": 0.1,
                "depth": 7,
                "rsm": 1.0,
                "loss_function": "Logloss",
                "eval_metric": "Logloss",
                "explain_level": 2
            },
            "name": "learner_fold_4",
            "best_ntree_limit": 235
        }
    ],
    "params": {
        "additional": {
            "max_rounds": 10000,
            "early_stopping_rounds": 50,
            "max_rows_limit": null,
            "max_cols_limit": null
        },
        "preprocessing": {
            "columns_preprocessing": {},
            "target_preprocessing": [
                "na_exclude"
            ],
            "ml_task": "binary_classification"
        },
        "validation_strategy": {
            "validation_type": "kfold",
            "k_folds": 5,
            "shuffle": true,
            "stratify": true,
            "X_path": "AutoML_classifier_Perform_last/X.data",
            "y_path": "AutoML_classifier_Perform_last/y.data",
            "results_path": "AutoML_classifier_Perform_last"
        },
        "learner": {
            "model_type": "CatBoost",
            "ml_task": "binary_classification",
            "n_jobs": -1,
            "seed": 1237,
            "learning_rate": 0.1,
            "depth": 7,
            "rsm": 1.0,
            "loss_function": "Logloss",
            "eval_metric": "Logloss",
            "explain_level": 2
        },
        "automl_random_state": 1234,
        "ml_task": "binary_classification",
        "explain_level": 2,
        "name": "15_CatBoost",
        "status": "initialized",
        "final_loss": null,
        "train_time": null,
        "data_type": "original",
        "max_time_for_learner": 72.0
    },
    "saved": [
        "15_CatBoost/learner_fold_0.catboost",
        "15_CatBoost/learner_fold_1.catboost",
        "15_CatBoost/learner_fold_2.catboost",
        "15_CatBoost/learner_fold_3.catboost",
        "15_CatBoost/learner_fold_4.catboost"
    ],
    "predictions_fname": "15_CatBoost/predictions_out_of_folds.csv",
    "metric_name": "logloss",
    "final_loss": 0.013153720592160955,
    "train_time": 54.87924242019653,
    "is_stacked": false,
    "threshold": 0.43618190681243013,
    "single_prediction_time": 0.034332990646362305
}